nycparser/__init__.py
nycparser/nycparser.py
tests/__init__.py
tests/test_address.py
tests/test_bbl.py
tests/test_complex_address.py
tests/testcase.py
nyc_parser-0.1.1.dist-info/METADATA
nyc_parser-0.1.1.dist-info/WHEEL
nyc_parser-0.1.1.dist-info/top_level.txt
nyc_parser-0.1.1.dist-info/RECORD
