Metadata-Version: 2.1
Name: nyc-parser
Version: 0.1.1
Summary: A parser for New York City addresses and BBL values
Home-page: https://github.com/ishiland/nyc-parser
Author: Ian Shiland
Author-email: ishiland@gmail.com
Classifier: Programming Language :: Python :: 3
Classifier: Programming Language :: Python :: 3.8
Classifier: Programming Language :: Python :: 3.9
Classifier: Programming Language :: Python :: 3.10
Classifier: Programming Language :: Python :: 3.11
Classifier: Programming Language :: Python :: 3.12
Classifier: Programming Language :: Python :: 3.13
Classifier: License :: OSI Approved :: MIT License
Classifier: Operating System :: OS Independent
Requires-Python: >=3.8
Provides-Extra: docs
Requires-Dist: sphinx >=4.0.0 ; extra == 'docs'
Requires-Dist: sphinx-rtd-theme >=1.0.0 ; extra == 'docs'
